lekkersim/__init__.py
lekkersim/_version.py
lekkersim/log.py
lekkersim/model.py
lekkersim/nazca_integration.py
lekkersim/pin.py
lekkersim/scattering.py
lekkersim/sol.py
lekkersim/structure.py
lekkersim/utils.py
lekkersim-0.1.1.dist-info/METADATA
lekkersim-0.1.1.dist-info/WHEEL
lekkersim-0.1.1.dist-info/licenses/LICENSE.md
lekkersim-0.1.1.dist-info/RECORD
